dwdsmor/__init__.py
dwdsmor/__main__.py
dwdsmor/cli.py
dwdsmor/log.py
dwdsmor/spacy.py
dwdsmor/traversal.py
dwdsmor/util.py
dwdsmor/version.py
dwdsmor/automata/BUILT
dwdsmor/automata/EDITION
dwdsmor/automata/GIT_REV
dwdsmor/automata/finite.a
dwdsmor/automata/finite.ca
dwdsmor/automata/index.a
dwdsmor/automata/index.ca
dwdsmor/automata/lemma.a
dwdsmor/automata/lemma.ca
dwdsmor/automata/lemma2.a
dwdsmor/automata/lemma2.ca
dwdsmor/automata/ppm.csv
dwdsmor/automata/root.a
dwdsmor/automata/root.ca
dwdsmor/automata/root2.a
dwdsmor/automata/root2.ca
dwdsmor/build/__init__.py
dwdsmor/build/__main__.py
dwdsmor/build/benchmark.py
dwdsmor/build/dwdswb.py
dwdsmor/build/traversal.py
dwdsmor/build/ud.py
dwdsmor/build/util.py
dwdsmor/build/wb_coverage.py
dwdsmor/tag/__init__.py
dwdsmor/tag/hdt.py
dwdsmor/tools/__init__.py
dwdsmor/tools/analysis.py
dwdsmor/tools/paradigm.py
dwdsmor-0.15.1.dist-info/licenses/COPYING
dwdsmor-0.15.1.dist-info/METADATA
dwdsmor-0.15.1.dist-info/WHEEL
dwdsmor-0.15.1.dist-info/entry_points.txt
dwdsmor-0.15.1.dist-info/top_level.txt
dwdsmor-0.15.1.dist-info/RECORD
