Metadata-Version: 2.4
Name: dwdsmor
Version: 0.15.1
Summary: SFST/SMOR/DWDS-based German morphology
Author-email: Andreas Nolda <andreas.nolda@bbaw.de>, Gregor Middell <gregor.middell@bbaw.de>
License-Expression: GPL-2.0-only
Project-URL: Homepage, https://github.com/zentrum-lexikographie/dwdsmor
Classifier: Development Status :: 1 - Planning
Classifier: Intended Audience :: Developers
Classifier: Intended Audience :: Science/Research
Classifier: Programming Language :: Python :: 3.10
Classifier: Programming Language :: Python :: 3.11
Classifier: Programming Language :: Python :: 3.12
Classifier: Programming Language :: Python :: 3.13
Classifier: Programming Language :: Python :: 3.14
Classifier: Topic :: Education
Classifier: Topic :: Scientific/Engineering
Classifier: Topic :: Text Processing :: Linguistic
Requires-Python: >=3.12
License-File: COPYING
Requires-Dist: blessings
Requires-Dist: PyYAML
Requires-Dist: sfst-transduce
Requires-Dist: tabulate
Requires-Dist: tqdm
Provides-Extra: dev
Requires-Dist: build; extra == "dev"
Requires-Dist: coverage; extra == "dev"
Requires-Dist: conllu; extra == "dev"
Requires-Dist: de_zdl_lg; extra == "dev"
Requires-Dist: flake8; extra == "dev"
Requires-Dist: flake8-bugbear; extra == "dev"
Requires-Dist: mypy; extra == "dev"
Requires-Dist: pre-commit; extra == "dev"
Requires-Dist: pytest; extra == "dev"
Requires-Dist: spacy; extra == "dev"
Requires-Dist: syrupy; extra == "dev"
Requires-Dist: twine; extra == "dev"
Requires-Dist: Jinja2; extra == "dev"
Dynamic: license-file
